{
  "requiresAttributes": [
    {
      "value": null,
      "name": "com.amazonaws.ecs.capability.docker-remote-api.1.17",
      "targetId": null,
      "targetType": null
    }
  ],
  "taskDefinitionArn": "arn:aws:ecs:us-west-2:665110747825:task-definition/LinuxbrewTestBot:1",
  "networkMode": "bridge",
  "status": "ACTIVE",
  "revision": 1,
  "taskRoleArn": null,
  "containerDefinitions": [
    {
      "volumesFrom": [],
      "memory": 512,
      "extraHosts": null,
      "dnsServers": null,
      "disableNetworking": null,
      "dnsSearchDomains": null,
      "portMappings": [],
      "hostname": null,
      "essential": true,
      "entryPoint": [],
      "mountPoints": [],
      "name": "LinuxbrewTestBot",
      "ulimits": null,
      "dockerSecurityOptions": null,
      "environment": [],
      "links": null,
      "workingDirectory": "/home/linuxbrew",
      "readonlyRootFilesystem": null,
      "image": "linuxbrew/linuxbrew",
      "command": [
        "/home/linuxbrew/.linuxbrew/bin/brew"
      ],
      "user": null,
      "dockerLabels": null,
      "logConfiguration": null,
      "cpu": 0,
      "privileged": null,
      "memoryReservation": null
    }
  ],
  "placementConstraints": [],
  "volumes": [],
  "family": "LinuxbrewTestBot"
}
